trino_mcp_navi/__init__.py
trino_mcp_navi/__main__.py
trino_mcp_navi/analytics.py
trino_mcp_navi/connection.py
trino_mcp_navi/server.py
trino_mcp_navi/utils/__init__.py
trino_mcp_navi/utils/query.py
trino_mcp_navi/utils/sql.py
trino_mcp_navi-0.2.1.dist-info/METADATA
trino_mcp_navi-0.2.1.dist-info/WHEEL
trino_mcp_navi-0.2.1.dist-info/entry_points.txt
trino_mcp_navi-0.2.1.dist-info/licenses/LICENSE
trino_mcp_navi-0.2.1.dist-info/RECORD
