Metadata-Version: 2.4
Name: trino-mcp-navi
Version: 0.2.1
Summary: A Model Context Protocol (MCP) server for Trino databases - gives AI assistants direct access to query and explore your data warehouse
Project-URL: Homepage, https://github.com/manish-coder-1007/trino-mcp-navi
Project-URL: Documentation, https://github.com/manish-coder-1007/trino-mcp-navi#readme
Project-URL: Repository, https://github.com/manish-coder-1007/trino-mcp-navi
Project-URL: Issues, https://github.com/manish-coder-1007/trino-mcp-navi/issues
Author: Manish Balot
License-Expression: MIT
License-File: LICENSE
Keywords: ai,claude,cursor,data-warehouse,database,llm,mcp,model-context-protocol,presto,trino
Classifier: Development Status :: 4 - Beta
Classifier: Intended Audience :: Developers
Classifier: Intended Audience :: Science/Research
Classifier: License :: OSI Approved :: MIT License
Classifier: Operating System :: OS Independent
Classifier: Programming Language :: Python :: 3
Classifier: Programming Language :: Python :: 3.10
Classifier: Programming Language :: Python :: 3.11
Classifier: Programming Language :: Python :: 3.12
Classifier: Topic :: Database
Classifier: Topic :: Scientific/Engineering :: Artificial Intelligence
Requires-Python: >=3.10
Requires-Dist: mcp>=1.0.0
Requires-Dist: openpyxl>=3.1.0
Requires-Dist: pandas>=2.0.0
Requires-Dist: posthog>=3.0.0
Requires-Dist: pyarrow>=14.0.0
Requires-Dist: starlette>=0.27.0
Requires-Dist: tabulate>=0.9.0
Requires-Dist: trino>=0.328.0
Requires-Dist: uvicorn>=0.23.0
Provides-Extra: dev
Requires-Dist: black>=23.0.0; extra == 'dev'
Requires-Dist: pytest-asyncio>=0.21.0; extra == 'dev'
Requires-Dist: pytest>=7.0.0; extra == 'dev'
Requires-Dist: ruff>=0.1.0; extra == 'dev'
